aievents/__init__.py
aievents/aievents.py
aievents/events.py
aievents/tests/__init__.py
aievents/tests/tests.py
asyncio-events/__init__.py
asyncio-events/events.py
asyncio-events/tests/__init__.py
asyncio-events/tests/tests.py
asyncio_events-0.1.4.dist-info/AUTHORS
asyncio_events-0.1.4.dist-info/LICENSE
asyncio_events-0.1.4.dist-info/METADATA
asyncio_events-0.1.4.dist-info/WHEEL
asyncio_events-0.1.4.dist-info/top_level.txt
asyncio_events-0.1.4.dist-info/RECORD
