Metadata-Version: 2.1
Name: asyncio-events
Version: 0.1.4
Summary: Events inspired by C# EventHandler supporting async methods
Home-page: https://github.com/ondrejnovakcvut/asyncio-events
Author: Ondrej Novak
Author-email: ondrej.novak.2@cvut.cz
License: BSD
Platform: any
Classifier: Programming Language :: Python :: 3.5
Classifier: Programming Language :: Python :: 3.6
Classifier: Programming Language :: Python :: 3.7
Classifier: Topic :: Software Development
